{
  "type" : "FeatureCollection",
  "crs" : {
    "type" : "name",
    "properties" : {
      "name" : "EPSG:4326"
    }
  },
  "features" : [
    {
      "type" : "Feature",
      "id" : 0,
      "geometry" : {
        "type" : "Polygon",
        "coordinates" : [
          [
            [
              117.37904027942898,
              31.874378811856502
            ],
            [
              117.37916645858083,
              31.874464335044152
            ],
            [
              117.3791233436945,
              31.874519582387851
            ],
            [
              117.37888740034403,
              31.874806617006683
            ],
            [
              117.37853985784771,
              31.875155067491178
            ],
            [
              117.37811175884156,
              31.875498029978875
            ],
            [
              117.37778813981566,
              31.875680335103851
            ],
            [
              117.37742880584844,
              31.875881834181868
            ],
            [
              117.37715640120511,
              31.876006719404927
            ],
            [
              117.37681038544207,
              31.876183361852586
            ],
            [
              117.37652077416516,
              31.876478186600046
            ],
            [
              117.37635369885211,
              31.87665048002237
            ],
            [
              117.37626271940195,
              31.876832092428039
            ],
            [
              117.37627678529081,
              31.87699048743071
            ],
            [
              117.37650657351411,
              31.877386853162907
            ],
            [
              117.3765562379409,
              31.877497420824778
            ],
            [
              117.37661051628507,
              31.877642334544333
            ],
            [
              117.37661382493999,
              31.877905749460535
            ],
            [
              117.37658786595404,
              31.878123438067171
            ],
            [
              117.37658163631728,
              31.87824180674669
            ],
            [
              117.37659306216652,
              31.878300948016715
            ],
            [
              117.37658064879658,
              31.879098894319743
            ],
            [
              117.37654658756985,
              31.879524674173297
            ],
            [
              117.37651886456646,
              31.879858809261854
            ],
            [
              117.37652293401804,
              31.880309291492285
            ],
            [
              117.37655199973823,
              31.880855143351617
            ],
            [
              117.37661299882137,
              31.881551701581397
            ],
            [
              117.376621216912,
              31.881921998709526
            ],
            [
              117.37666568736462,
              31.882404811942191
            ],
            [
              117.37666160927814,
              31.882502176565755
            ],
            [
              117.37669284386352,
              31.883030841913509
            ],
            [
              117.37671867996762,
              31.883332367312249
            ],
            [
              117.37674375479267,
              31.883446825390589
            ],
            [
              117.37674259766423,
              31.883712162168006
            ],
            [
              117.37673922668345,
              31.8839832321137
            ],
            [
              117.37675073885369,
              31.884063370658208
            ],
            [
              117.37674042327365,
              31.884277194985767
            ],
            [
              117.37671212477601,
              31.884470074994749
            ],
            [
              117.3767064543631,
              31.884725880740408
            ],
            [
              117.37668169806939,
              31.885239440824755
            ],
            [
              117.37666920718004,
              31.885468542533644
            ],
            [
              117.37665455671727,
              31.885716739355757
            ],
            [
              117.37667810194036,
              31.88600490931433
            ],
            [
              117.3767012432841,
              31.886193819096412
            ],
            [
              117.37674465182793,
              31.886415119632471
            ],
            [
              117.37683074668944,
              31.886680197674728
            ],
            [
              117.37688064981971,
              31.8868480304765
            ],
            [
              117.376899472815,
              31.887075130436227
            ],
            [
              117.37688452734903,
              31.887250790963581
            ],
            [
              117.37680476384259,
              31.887441914605738
            ],
            [
              117.37668997321755,
              31.887822120298001
            ],
            [
              117.3766233837936,
              31.88795212087992
            ],
            [
              117.37656369239639,
              31.888127913911664
            ],
            [
              117.37646425024307,
              31.888431719037303
            ],
            [
              117.37636488508376,
              31.888754612560835
            ],
            [
              117.37630985356348,
              31.888976204573769
            ],
            [
              117.37616533018078,
              31.889198061412273
            ],
            [
              117.37606546668394,
              31.889398788382231
            ],
            [
              117.3759764479947,
              31.889515492856937
            ],
            [
              117.3759051879062,
              31.889597785071011
            ],
            [
              117.37582503275392,
              31.889693465642608
            ],
            [
              117.37581193455057,
              31.889773676960225
            ],
            [
              117.37581448971503,
              31.889851933126561
            ],
            [
              117.37574582309445,
              31.89002202565614
            ],
            [
              117.37569258491563,
              31.890134806412696
            ],
            [
              117.37566633389171,
              31.890281867072623
            ],
            [
              117.37564002854175,
              31.890415565787194
            ],
            [
              117.37547966964489,
              31.890595473446808
            ],
            [
              117.37528311802774,
              31.890678135338725
            ],
            [
              117.37507747746436,
              31.890726464068049
            ],
            [
              117.37484950979558,
              31.890786311534548
            ],
            [
              117.37471779341537,
              31.890857328116908
            ],
            [
              117.37464902356867,
              31.89100260502158
            ],
            [
              117.374674492225,
              31.891214414629893
            ],
            [
              117.37467516470279,
              31.891380484416
            ],
            [
              117.37476519190884,
              31.891511931109541
            ],
            [
              117.37495586142471,
              31.891633536545843
            ],
            [
              117.37511071832753,
              31.89175142963926
            ],
            [
              117.37526094607689,
              31.891831158792744
            ],
            [
              117.3753707003293,
              31.891861376657609
            ],
            [
              117.37549629431591,
              31.891935451661002
            ],
            [
              117.37577227215813,
              31.892127432030144
            ],
            [
              117.37596302182361,
              31.892268124399642
            ],
            [
              117.37601276359536,
              31.892395871586295
            ],
            [
              117.37601107701339,
              31.892531406375408
            ],
            [
              117.37587264295769,
              31.893152198663763
            ],
            [
              117.37580391978425,
              31.893308929223664
            ],
            [
              117.37563434317406,
              31.893423962685933
            ],
            [
              117.37545135726235,
              31.89354285327132
            ],
            [
              117.37527745984228,
              31.893696076422696
            ],
            [
              117.37519517150503,
              31.89381848703486
            ],
            [
              117.37509770094361,
              31.894059292339744
            ],
            [
              117.37501819109184,
              31.894315315532285
            ],
            [
              117.37494928768922,
              31.894428142135755
            ],
            [
              117.37484269601896,
              31.894626978996801
            ],
            [
              117.3747675670529,
              31.894860082657889
            ],
            [
              117.3748387138855,
              31.895300821774885
            ],
            [
              117.37484137670894,
              31.89540580175381
            ],
            [
              117.37483070769038,
              31.895533727482945
            ],
            [
              117.37480422957825,
              31.895625431305717
            ],
            [
              117.37480698518007,
              31.895753317441233
            ],
            [
              117.37482334338756,
              31.8959250674597
            ],
            [
              117.3748621381114,
              31.896112022256716
            ],
            [
              117.37493656992326,
              31.896258785658176
            ],
            [
              117.37498651366303,
              31.896436163170087
            ],
            [
              117.37503201361262,
              31.896621189245888
            ],
            [
              117.37506633411542,
              31.896808157158667
            ],
            [
              117.37508487631119,
              31.896966538582948
            ],
            [
              117.37508779489818,
              31.897134510453967
            ],
            [
              117.37510852824583,
              31.897281432185416
            ],
            [
              117.37515898382537,
              31.897584793439716
            ],
            [
              117.3752118553286,
              31.897932051509805
            ],
            [
              117.37526444071852,
              31.898208682237694
            ],
            [
              117.37532329750219,
              31.898376488894787
            ],
            [
              117.37523404479529,
              31.898437836229085
            ],
            [
              117.37515932427993,
              31.898220445770225
            ],
            [
              117.37504318365693,
              31.897720664891253
            ],
            [
              117.37498346890801,
              31.89734097615187
            ],
            [
              117.37500484554994,
              31.897094668969014
            ],
            [
              117.37499320160526,
              31.896982080043703
            ],
            [
              117.37495217649645,
              31.896797040764127
            ],
            [
              117.3748861603452,
              31.896518540583127
            ],
            [
              117.3748609758112,
              31.896377358531428
            ],
            [
              117.37478643575369,
              31.896203871235716
            ],
            [
              117.37470289976606,
              31.896018957194013
            ],
            [
              117.37469796096441,
              31.895904439583621
            ],
            [
              117.37470153901103,
              31.895683000167619
            ],
            [
              117.37469450195266,
              31.89560284838965
            ],
            [
              117.37474125633672,
              31.895545444463018
            ],
            [
              117.37474543739521,
              31.895472895089842
            ],
            [
              117.37469361285467,
              31.895383331001874
            ],
            [
              117.37460919665584,
              31.89498080831131
            ],
            [
              117.37469352320939,
              31.894808761468102
            ],
            [
              117.3747267366733,
              31.894722764410126
            ],
            [
              117.37479120438672,
              31.894619495359123
            ],
            [
              117.37488227346986,
              31.894455063982235
            ],
            [
              117.37497563380234,
              31.89430398786779
            ],
            [
              117.37504170384065,
              31.894044186617112
            ],
            [
              117.37518569551456,
              31.893688711837903
            ],
            [
              117.37545752719775,
              31.893409214134394
            ],
            [
              117.37555564701668,
              31.893328751717704
            ],
            [
              117.37574969527039,
              31.893179286355892
            ],
            [
              117.37591505620432,
              31.892577503273237
            ],
            [
              117.37593697231685,
              31.892464815102343
            ],
            [
              117.37591867782625,
              31.892367516815565
            ],
            [
              117.3758197994861,
              31.892260912454745
            ],
            [
              117.37559312054648,
              31.89208787523998
            ],
            [
              117.37537556225203,
              31.891956805832272
            ],
            [
              117.3752770333774,
              31.891936099185124
            ],
            [
              117.37508862338538,
              31.89182021418592
            ],
            [
              117.37500330221489,
              31.891746019970089
            ],
            [
              117.37482387327931,
              31.891637743558562
            ],
            [
              117.3747072991949,
              31.891580821131175
            ],
            [
              117.37461726427414,
              31.891447465549795
            ],
            [
              117.37450244115577,
              31.891270278903633
            ],
            [
              117.37450811014685,
              31.891012564621388
            ],
            [
              117.3745500167983,
              31.890863549207289
            ],
            [
              117.37474630662243,
              31.890715987602327
            ],
            [
              117.37495864384847,
              31.890663821912376
            ],
            [
              117.37521582795024,
              31.89063633882084
            ],
            [
              117.37530720212683,
              31.890548261001157
            ],
            [
              117.37553273016046,
              31.890438789275414
            ],
            [
              117.37557496806801,
              31.890371853997728
            ],
            [
              117.37562813678318,
              31.890241893658477
            ],
            [
              117.37564104922686,
              31.890115870005872
            ],
            [
              117.37560265848852,
              31.890028175375253
            ],
            [
              117.37569798704477,
              31.889812191214173
            ],
            [
              117.37576274486604,
              31.889781457862519
            ],
            [
              117.37577362131437,
              31.889705070860249
            ],
            [
              117.37583141128158,
              31.88961136531902
            ],
            [
              117.37598519552697,
              31.889465836329663
            ],
            [
              117.37610287226026,
              31.889244059135585
            ],
            [
              117.37625183162845,
              31.889012644881621
            ],
            [
              117.37636445807982,
              31.88864962589188
            ],
            [
              117.37644165233685,
              31.888376428683078
            ],
            [
              117.37658087585577,
              31.887952246812798
            ],
            [
              117.37664747310903,
              31.887824155101445
            ],
            [
              117.37675128749906,
              31.887495521517586
            ],
            [
              117.37683978249173,
              31.887250923613436
            ],
            [
              117.37684802410006,
              31.887077191836447
            ],
            [
              117.37682717386005,
              31.886901637422316
            ],
            [
              117.37674775162526,
              31.886626995252065
            ],
            [
              117.37667974906105,
              31.886409585346332
            ],
            [
              117.37663630183215,
              31.886178740540579
            ],
            [
              117.3765904311938,
              31.885902089953966
            ],
            [
              117.37659137123089,
              31.885583305482307
            ],
            [
              117.37662316592242,
              31.885149897236396
            ],
            [
              117.37663687644951,
              31.88467072958894
            ],
            [
              117.37668147216955,
              31.884084573515899
            ],
            [
              117.37668734733232,
              31.883466797097228
            ],
            [
              117.37665696515263,
              31.883216347523589
            ],
            [
              117.37663434616047,
              31.882811972029362
            ],
            [
              117.37661624238459,
              31.882486324154865
            ],
            [
              117.37658029735674,
              31.881899452050682
            ],
            [
              117.3765575043581,
              31.881452127314287
            ],
            [
              117.37650941329419,
              31.880972665218454
            ],
            [
              117.37649112114119,
              31.880600488984527
            ],
            [
              117.37645658966426,
              31.880360788946994
            ],
            [
              117.37646837341568,
              31.879820304080187
            ],
            [
              117.37647464856151,
              31.87964431115951
            ],
            [
              117.37655177925269,
              31.878841759000366
            ],
            [
              117.37655702295474,
              31.878412246705157
            ],
            [
              117.37653552915356,
              31.878284057850433
            ],
            [
              117.3764897984406,
              31.878212610477803
            ],
            [
              117.3764927600734,
              31.878081366574897
            ],
            [
              117.37654130670812,
              31.877985779074251
            ],
            [
              117.3765406152193,
              31.877815771966617
            ],
            [
              117.37651171849514,
              31.877586196044835
            ],
            [
              117.37642721213869,
              31.877434332803404
            ],
            [
              117.37628673251803,
              31.877270704700592
            ],
            [
              117.37619131670313,
              31.87701448197603
            ],
            [
              117.37616921780749,
              31.876737163951194
            ],
            [
              117.37623527690808,
              31.876650472587684
            ],
            [
              117.37642659630336,
              31.876423227383679
            ],
            [
              117.37662161630104,
              31.876246675424625
            ],
            [
              117.37682719420309,
              31.876087987580032
            ],
            [
              117.37708528540097,
              31.875950021994431
            ],
            [
              117.37738166563696,
              31.875773168216973
            ],
            [
              117.3776899358925,
              31.875598068000869
            ],
            [
              117.37790490250931,
              31.87551391596585
            ],
            [
              117.37817265533965,
              31.875346093282133
            ],
            [
              117.37842603614887,
              31.875082869041972
            ],
            [
              117.37904027942898,
              31.874378811856502
            ]
          ]
        ]
      },
      "properties" : {
        "FID" : 0,
        "Name" : "WestStreamDown",
        "Watershed" : "XiaoBanQiao",
        "CNName" : "小板桥河西支下",
        "Width" : 0,
        "Length" : 0,
        "Index" : " "
      }
    }
  ]
}